{
  "tasks": {
    "dev": "deno run --allow-read --allow-env --allow-net --watch server.ts",
    "start": "deno run --allow-read --allow-env --allow-net server.ts"
  },
  "imports": {
    "@arcjet/analyze-wasm": "../../analyze-wasm/dist/index.js",
    "@arcjet/analyze": "../../analyze/dist/index.js",
    "npm:@arcjet/deno": "../../arcjet-deno/dist/index.js",
    "@arcjet/body": "../../body/dist/index.js",
    "@arcjet/duration": "../../duration/dist/index.js",
    "@arcjet/cache": "../../cache/dist/index.js",
    "@arcjet/env": "../../env/dist/index.js",
    "@arcjet/headers": "../../headers/dist/index.js",
    "@arcjet/ip": "../../ip/dist/index.js",
    "@arcjet/logger": "../../logger/dist/index.js",
    "@arcjet/protocol": "../../protocol/dist/index.js",
    "@arcjet/protocol/client.js": "../../protocol/dist/client.js",
    "@arcjet/protocol/convert.js": "../../protocol/dist/convert.js",
    "@arcjet/runtime": "../../runtime/dist/index.js",
    "@arcjet/sprintf": "../../sprintf/dist/index.js",
    "@arcjet/stable-hash": "../../stable-hash/dist/index.js",
    "@arcjet/transport": "../../transport/dist/index.js",
    "@bufbuild/protobuf": "npm:@bufbuild/protobuf@2.11.0",
    "@connectrpc/connect": "npm:@connectrpc/connect@2.1.1",
    "@connectrpc/connect-node": "npm:@connectrpc/connect-node@2.1.1",
    "arcjet": "../../arcjet/dist/index.js",
    "typeid-js": "npm:typeid-js@1.2.0"
  }
}
